Workbook

Sheet Statements
A2: x
B4: Income Statement | D4: 45292 | E4: 45323 | F4: 45352 | G4: 45383 | H4: 45413 | I4: 45444 | J4: 45474 | K4: 45505 | L4: 45536 | M4: 45566 | N4: 45597 | O4: 45627
B5: Total Revenue | D5: 100000 | E5: 106000 | F5: 112000 | G5: 120000 | H5: 128000 | I5: 137000 | J5: 148000 | K5: 160000 | L5: 172000 | M5: 185000 | N5: 200000 | O5: 215000
B6: COGS | D6: 20000 | E6: 21000 | F6: 22000 | G6: 24000 | H6: 25000 | I6: 27000 | J6: 29000 | K6: 32000 | L6: 34000 | M6: 37000 | N6: 40000 | O6: 43000
B7: Gross Profit | D7: =D5-D6 -> 80000 | E7: =E5-E6 -> 85000 | F7: =F5-F6 -> 90000 | G7: =G5-G6 -> 96000 | H7: =H5-H6 -> 103000 | I7: =I5-I6 -> 110000 | J7: =J5-J6 -> 119000 | K7: =K5-K6 -> 128000 | ... O7: =O5-O6 -> 172000
B8: Sales Marketing | D8: 40000 | E8: 45000 | F8: 50000 | G8: 55000 | H8: 60000 | I8: 65000 | J8: 70000 | K8: 75000 | L8: 80000 | M8: 85000 | N8: 90000 | O8: 100000
B9: R&D | D9: 50000 | E9: 50000 | F9: 50000 | G9: 60000 | H9: 60000 | I9: 60000 | J9: 70000 | K9: 70000 | L9: 70000 | M9: 80000 | N9: 80000 | O9: 80000
B10: G&A | D10: 20000 | E10: 20000 | F10: 20000 | G10: 20000 | H10: 25000 | I10: 25000 | J10: 25000 | K10: 25000 | L10: 25000 | M10: 30000 | N10: 30000 | O10: 30000
B11: Total Opex | D11: =SUM(D8:D10) -> 110000 | E11: =SUM(E8:E10) -> 115000 | F11: =SUM(F8:F10) -> 120000 | G11: =SUM(G8:G10) -> 135000 | H11: =SUM(H8:H10) -> 145000 | I11: =SUM(I8:I10) -> 150000 | J11: =SUM(J8:J10) -> 165000 | K11: =SUM(K8:K10) -> 170000 | ... O11: =SUM(O8:O10) -> 210000
B12: Operating Income | D12: =D7-D11 -> -30000 | E12: =E7-E11 -> -30000 | F12: =F7-F11 -> -30000 | G12: =G7-G11 -> -39000 | H12: =H7-H11 -> -42000 | I12: =I7-I11 -> -40000 | J12: =J7-J11 -> -46000 | K12: =K7-K11 -> -42000 | ... O12: =O7-O11 -> -38000
B13: Interest Expense | D13: 0 | E13: 0 | F13: 0 | G13: 0 | H13: 0 | I13: 0 | J13: 0 | K13: 0 | L13: 0 | M13: 0 | N13: 0 | O13: 0
B14: Interest Income | D14: 0 | E14: 0 | F14: 0 | G14: 0 | H14: 0 | I14: 0 | J14: 0 | K14: 0 | L14: 0 | M14: 0 | N14: 0 | O14: 0
B15: Pretax Profit | D15: =D12 -> -30000 | E15: =E12 -> -30000 | F15: =F12 -> -30000 | G15: =G12 -> -39000 | H15: =H12 -> -42000 | I15: =I12 -> -40000 | J15: =J12 -> -46000 | K15: =K12 -> -42000 | ... O15: =O12 -> -38000
B16: Tax | D16: 0 | E16: 0 | F16: 0 | G16: 0 | H16: 0 | I16: 0 | J16: 0 | K16: 0 | L16: 0 | M16: 0 | N16: 0 | O16: 0
B17: Net Income | D17: =D7-D11 -> -30000 | E17: =E7-E11 -> -30000 | F17: =F7-F11 -> -30000 | G17: =G7-G11 -> -39000 | H17: =H7-H11 -> -42000 | I17: =I7-I11 -> -40000 | J17: =J7-J11 -> -46000 | K17: =K7-K11 -> -42000 | ... O17: =O7-O11 -> -38000
A20: x | B20: Balance Sheet | D20: 45292 | E20: 45323 | F20: 45352 | G20: 45383 | H20: 45413 | I20: 45444 | J20: 45474 | K20: 45505 | L20: 45536 | M20: 45566 | N20: 45597 | O20: 45627
B22: Cash | D22: =D44 -> 530000 | E22: =E44 -> 500000 | F22: =F44 -> 470000 | G22: =G44 -> 440000 | H22: =H44 -> 401000 | I22: =I44 -> 359000 | J22: =J44 -> 319000 | K22: =K44 -> 273000 | ... O22: =O44 -> 1107000
B23: Accounts Receviable | D23: =D5 -> 100000 | E23: =E5 -> 106000 | F23: =F5 -> 112000 | G23: =G5 -> 120000 | H23: =H5 -> 128000 | I23: =I5 -> 137000 | J23: =J5 -> 148000 | K23: =K5 -> 160000 | ... O23: =O5 -> 215000
B24: Total Assets | D24: =SUM(D22:D23) -> 630000 | E24: =SUM(E22:E23) -> 606000 | F24: =SUM(F22:F23) -> 582000 | G24: =SUM(G22:G23) -> 560000 | H24: =SUM(H22:H23) -> 529000 | I24: =SUM(I22:I23) -> 496000 | J24: =SUM(J22:J23) -> 467000 | K24: =SUM(K22:K23) -> 433000 | ... O24: =SUM(O22:O23) -> 1322000
B25: Accounts Payable | D25: =D6+D11 -> 130000 | E25: =E6+E11 -> 136000 | F25: =F6+F11 -> 142000 | G25: =G6+G11 -> 159000 | H25: =H6+H11 -> 170000 | I25: =I6+I11 -> 177000 | J25: =J6+J11 -> 194000 | K25: =K6+K11 -> 202000 | ... O25: =O6+O11 -> 253000
B26: Share capital | D26: 1000000 | E26: 1000000 | F26: 1000000 | G26: 1000000 | H26: 1000000 | I26: 1000000 | J26: 1000000 | K26: 1000000 | L26: 1000000 | M26: 1000000 | N26: 2000000 | O26: 2000000
B27: Retained Earnings | D27: =-470000+D17 -> -500000 | E27: =D27+E17 -> -530000 | F27: =E27+F17 -> -560000 | G27: =F27+G17 -> -599000 | H27: =G27+H17 -> -641000 | I27: =H27+I17 -> -681000 | J27: =I27+J17 -> -727000 | K27: =J27+K17 -> -769000 | L27: =K27+L17 -> -806000 | ... O27: =N27+O17 -> -931000
B28: Total liabilites & Equity | D28: =SUM(D25:D27) -> 630000 | E28: =SUM(E25:E27) -> 606000 | F28: =SUM(F25:F27) -> 582000 | G28: =SUM(G25:G27) -> 560000 | H28: =SUM(H25:H27) -> 529000 | I28: =SUM(I25:I27) -> 496000 | J28: =SUM(J25:J27) -> 467000 | K28: =SUM(K25:K27) -> 433000 | ... O28: =SUM(O25:O27) -> 1322000
A31: x | B31: Cash Flow Statement | D31: 45292 | E31: 45323 | F31: 45352 | G31: 45383 | H31: 45413 | I31: 45444 | J31: 45474 | K31: 45505 | L31: 45536 | M31: 45566 | N31: 45597 | O31: 45627
B33: Net Income | D33: =D17 -> -30000 | E33: =E17 -> -30000 | F33: =F17 -> -30000 | G33: =G17 -> -39000 | H33: =H17 -> -42000 | I33: =I17 -> -40000 | J33: =J17 -> -46000 | K33: =K17 -> -42000 | ... O33: =O17 -> -38000
B34: Accounts Receviable | D34: =-(D23-0) -> -100000 | E34: =-(E23-D23) -> -6000 | F34: =-(F23-E23) -> -6000 | G34: =-(G23-F23) -> -8000 | H34: =-(H23-G23) -> -8000 | I34: =-(I23-H23) -> -9000 | J34: =-(J23-I23) -> -11000 | K34: =-(K23-J23) -> -12000 | L34: =-(L23-K23) -> -12000 | ... O34: =-(O23-N23) -> -15000
B35: Accounts Payable | D35: =D25-0 -> 130000 | E35: =E25-D25 -> 6000 | F35: =F25-E25 -> 6000 | G35: =G25-F25 -> 17000 | H35: =H25-G25 -> 11000 | I35: =I25-H25 -> 7000 | J35: =J25-I25 -> 17000 | K35: =K25-J25 -> 8000 | L35: =L25-K25 -> 7000 | ... O35: =O25-N25 -> 13000
B36: Net cash from ops | D36: =SUM(D33:D35) -> 0 | E36: =SUM(E33:E35) -> -30000 | F36: =SUM(F33:F35) -> -30000 | G36: =SUM(G33:G35) -> -30000 | H36: =SUM(H33:H35) -> -39000 | I36: =SUM(I33:I35) -> -42000 | J36: =SUM(J33:J35) -> -40000 | K36: =SUM(K33:K35) -> -46000 | ... O36: =SUM(O33:O35) -> -40000
B38: New Funding | D38: 0 | E38: 0 | F38: 0 | G38: 0 | H38: 0 | I38: 0 | J38: 0 | K38: 0 | L38: 0 | M38: 0 | N38: 1000000 | O38: 0
B39: Net cash from Financing | D39: =D38 -> 0 | E39: =E38 -> 0 | F39: =F38 -> 0 | G39: =G38 -> 0 | H39: =H38 -> 0 | I39: =I38 -> 0 | J39: =J38 -> 0 | K39: =K38 -> 0 | ... O39: =O38 -> 0
B41: Net change in cash | D41: =D36+D39 -> 0 | E41: =E36+E39 -> -30000 | F41: =F36+F39 -> -30000 | G41: =G36+G39 -> -30000 | H41: =H36+H39 -> -39000 | I41: =I36+I39 -> -42000 | J41: =J36+J39 -> -40000 | K41: =K36+K39 -> -46000 | ... O41: =O36+O39 -> -40000
B42: Beginning Cash | D42: 530000 | E42: =D44 -> 530000 | F42: =E44 -> 500000 | G42: =F44 -> 470000 | H42: =G44 -> 440000 | I42: =H44 -> 401000 | J42: =I44 -> 359000 | K42: =J44 -> 319000 | L42: =K44 -> 273000 | ... O42: =N44 -> 1147000
B44: Ending Cash | D44: =D42+D41 -> 530000 | E44: =E42+E41 -> 500000 | F44: =F42+F41 -> 470000 | G44: =G42+G41 -> 440000 | H44: =H42+H41 -> 401000 | I44: =I42+I41 -> 359000 | J44: =J42+J41 -> 319000 | K44: =K42+K41 -> 273000 | ... O44: =O42+O41 -> 1107000
B47: Gross Margin | D47: =D7/D5 -> 0.8 | E47: =E7/E5 -> 0.80188679 | F47: =F7/F5 -> 0.80357143 | G47: =G7/G5 -> 0.8 | H47: =H7/H5 -> 0.8046875 | I47: =I7/I5 -> 0.80291971 | J47: =J7/J5 -> 0.80405405 | K47: =K7/K5 -> 0.8 | ... O47: =O7/O5 -> 0.8
N54: Created By : Vishwaradhya Ms | FP&A Startup Finance Analyst
N55: Model created manually for demonstration purpose

Sheet KPI's
C4: 45292 | D4: 45323 | E4: 45352 | F4: 45383 | G4: 45413 | H4: 45444 | I4: 45474 | J4: 45505 | K4: 45536 | L4: 45566 | M4: 45597 | N4: 45627
B6: Start customers | C6: 1000 | D6: 1050 | E6: 1110 | F6: 1180 | G6: 1260 | H6: 1350 | I6: 1450 | J6: 1560 | K6: 1680 | L6: 1810 | M6: 1950 | N6: 2100
B8: New Customers | C8: 80 | D8: 90 | E8: 100 | F8: 110 | G8: 120 | H8: 130 | I8: 140 | J8: 150 | K8: 160 | L8: 170 | M8: 180 | N8: 200
B10: Churned Cust | C10: 30 | D10: 30 | E10: 30 | F10: 30 | G10: 30 | H10: 30 | I10: 30 | J10: 30 | K10: 30 | L10: 30 | M10: 30 | N10: 30
B14: CAC(Customer Acquisition Cost)
B15: Sales & Marketing Expense (from P&L) / New Customers | C15: =Statements!D8/'KPI''s'!C8 -> 500 | D15: =Statements!E8/'KPI''s'!D8 -> 500 | E15: =Statements!F8/'KPI''s'!E8 -> 500 | F15: =Statements!G8/'KPI''s'!F8 -> 500 | G15: =Statements!H8/'KPI''s'!G8 -> 500 | H15: =Statements!I8/'KPI''s'!H8 -> 500 | I15: =Statements!J8/'KPI''s'!I8 -> 500 | J15: =Statements!K8/'KPI''s'!J8 -> 500 | ... N15: =Statements!O8/'KPI''s'!N8 -> 500
B17: ARPU (Average Revenue Per User)
B18: Total Revenue (from P&L) / Start Customers | C18: =Statements!D5/'KPI''s'!C6 -> 100 | D18: =Statements!E5/'KPI''s'!D6 -> 100.95238 | E18: =Statements!F5/'KPI''s'!E6 -> 100.9009 | F18: =Statements!G5/'KPI''s'!F6 -> 101.69492 | G18: =Statements!H5/'KPI''s'!G6 -> 101.5873 | H18: =Statements!I5/'KPI''s'!H6 -> 101.48148 | I18: =Statements!J5/'KPI''s'!I6 -> 102.06897 | J18: =Statements!K5/'KPI''s'!J6 -> 102.5641 | ... N18: =Statements!O5/'KPI''s'!N6 -> 102.38095
B20: LTV (Lifetime Value)
B21: (ARPU * Gross Margin %) / Churn Rate % | C21: =C18*(Statements!D47/'KPI''s'!C32) -> 2666.6667 | D21: =D18*(Statements!E47/'KPI''s'!D32) -> 2833.3333 | E21: =E18*(Statements!F47/'KPI''s'!E32) -> 3000 | F21: =F18*(Statements!G47/'KPI''s'!F32) -> 3200 | G21: =G18*(Statements!H47/'KPI''s'!G32) -> 3433.3333 | H21: =H18*(Statements!I47/'KPI''s'!H32) -> 3666.6667 | I21: =I18*(Statements!J47/'KPI''s'!I32) -> 3966.6667 | J21: =J18*(Statements!K47/'KPI''s'!J32) -> 4266.6667 | ... N21: =N18*(Statements!O47/'KPI''s'!N32) -> 5733.3333
B23: LTV:CAC Ratio
B24: LTV / CAC | C24: =C21/C15 -> 5.3333333 | D24: =D21/D15 -> 5.6666667 | E24: =E21/E15 -> 6 | F24: =F21/F15 -> 6.4 | G24: =G21/G15 -> 6.8666667 | H24: =H21/H15 -> 7.3333333 | I24: =I21/I15 -> 7.9333333 | J24: =J21/J15 -> 8.5333333 | ... N24: =N21/N15 -> 11.466667
B32: Churn Rate | C32: =C10/C6 -> 0.03 | D32: =D10/D6 -> 0.028571429 | E32: =E10/E6 -> 0.027027027 | F32: =F10/F6 -> 0.025423729 | G32: =G10/G6 -> 0.023809524 | H32: =H10/H6 -> 0.022222222 | I32: =I10/I6 -> 0.020689655 | J32: =J10/J6 -> 0.019230769 | ... N32: =N10/N6 -> 0.014285714
N39: Created By : Vishwaradhya Ms | FP&A Startup Finance Analyst
N40: Model created manually for demonstration purpose
